odoo10_addon_medical_agpl-10.0.1.0.0-py2.7-nspkg.pth
odoo/addons/medical_agpl/README.rst
odoo/addons/medical_agpl/__init__.py
odoo/addons/medical_agpl/__manifest__.py
odoo/addons/medical_agpl/static/description/icon.png
odoo10_addon_medical_agpl-10.0.1.0.0.dist-info/DESCRIPTION.rst
odoo10_addon_medical_agpl-10.0.1.0.0.dist-info/METADATA
odoo10_addon_medical_agpl-10.0.1.0.0.dist-info/RECORD
odoo10_addon_medical_agpl-10.0.1.0.0.dist-info/WHEEL
odoo10_addon_medical_agpl-10.0.1.0.0.dist-info/metadata.json
odoo10_addon_medical_agpl-10.0.1.0.0.dist-info/namespace_packages.txt
odoo10_addon_medical_agpl-10.0.1.0.0.dist-info/top_level.txt
