Metadata-Version: 2.0
Name: odoo10-addon-medical-agpl
Version: 10.0.1.0.0
Summary: Odoo Medical - AGPL
Home-page: https://odoo-community.org/
Author: LasLabs, Odoo Community Association (OCA)
Author-email: support@odoo-community.org
License: AGPL-3
Platform: UNKNOWN
Classifier: Programming Language :: Python :: 2.7
Classifier: Framework :: Odoo
Classifier: License :: OSI Approved :: GNU Affero General Public License v3
Requires-Dist: odoo (<10.1dev,>=10.0)
Requires-Dist: odoo10-addon-medical
Requires-Dist: odoo10-addon-partner-contact-birthdate
Requires-Dist: odoo10-addon-partner-contact-gender
Requires-Dist: odoo10-addon-partner-contact-weight
Requires-Dist: odoo10-addon-partner-firstname
Requires-Dist: odoo10-addon-partner-identification
